aind_metadata_extractor/__init__.py
aind_metadata_extractor/core.py
aind_metadata_extractor/bergamo/__init__.py
aind_metadata_extractor/bergamo/extractor.py
aind_metadata_extractor/bergamo/settings.py
aind_metadata_extractor/fip/__init__.py
aind_metadata_extractor/fip/_generate_schema.py
aind_metadata_extractor/mesoscope/__init__.py
aind_metadata_extractor/mesoscope/extractor.py
aind_metadata_extractor/mesoscope/job_settings.py
aind_metadata_extractor/models/__init__.py
aind_metadata_extractor/models/bergamo.py
aind_metadata_extractor/models/fip.json
aind_metadata_extractor/models/mesoscope.py
aind_metadata_extractor/models/smartspim.py
aind_metadata_extractor/smartspim/__init__.py
aind_metadata_extractor/smartspim/extractor.py
aind_metadata_extractor/smartspim/job_settings.py
aind_metadata_extractor/smartspim/utils.py
aind_metadata_extractor/utils/__init__.py
aind_metadata_extractor/utils/camstim_sync/__init__.py
aind_metadata_extractor/utils/camstim_sync/behavior_utils.py
aind_metadata_extractor/utils/camstim_sync/camstim.py
aind_metadata_extractor/utils/camstim_sync/constants.py
aind_metadata_extractor/utils/camstim_sync/naming_utils.py
aind_metadata_extractor/utils/camstim_sync/pkl_utils.py
aind_metadata_extractor/utils/camstim_sync/stim_utils.py
aind_metadata_extractor/utils/camstim_sync/sync_utils.py
aind_metadata_extractor-0.3.7.dist-info/licenses/LICENSE
aind_metadata_extractor-0.3.7.dist-info/METADATA
aind_metadata_extractor-0.3.7.dist-info/WHEEL
aind_metadata_extractor-0.3.7.dist-info/top_level.txt
aind_metadata_extractor-0.3.7.dist-info/RECORD
