Metadata-Version: 2.4
Name: aind-metadata-extractor
Version: 0.3.7
Summary: Generated from aind-library-template
Author: Allen Institute for Neural Dynamics
License: MIT
Classifier: Programming Language :: Python :: 3
Requires-Python: >=3.10
License-File: LICENSE
Requires-Dist: pydantic
Requires-Dist: pydantic-settings
Provides-Extra: dev
Requires-Dist: black; extra == "dev"
Requires-Dist: coverage; extra == "dev"
Requires-Dist: flake8; extra == "dev"
Requires-Dist: interrogate; extra == "dev"
Requires-Dist: isort; extra == "dev"
Requires-Dist: Sphinx; extra == "dev"
Requires-Dist: furo; extra == "dev"
Provides-Extra: smartspim
Requires-Dist: requests; extra == "smartspim"
Provides-Extra: bergamo
Requires-Dist: scanimage-tiff-reader==1.4.1.4; extra == "bergamo"
Requires-Dist: numpy==1.26.4; extra == "bergamo"
Provides-Extra: utils
Requires-Dist: numpy>=1.26.4; extra == "utils"
Requires-Dist: h5py>=3.11.0; extra == "utils"
Requires-Dist: scipy>=1.11.0; extra == "utils"
Requires-Dist: pandas>=2.2.2; extra == "utils"
Provides-Extra: mesoscope
Requires-Dist: aind-metadata-extractor[bergamo]; extra == "mesoscope"
Requires-Dist: aind-metadata-extractor[utils]; extra == "mesoscope"
Requires-Dist: pillow>=10.4.0; extra == "mesoscope"
Requires-Dist: tifffile==2024.2.12; extra == "mesoscope"
Provides-Extra: fip
Requires-Dist: aind-physiology-fip[data]; extra == "fip"
Dynamic: license-file
